{
  "id": "294840a1-1678-4f78-b759-1922b280eb09",
  "prevId": "2dddace9-4f2e-4f88-8a10-dd1f070b6e1c",
  "version": "7",
  "dialect": "postgresql",
  "tables": {
    "public.contact": {
      "name": "contact",
      "schema": "",
      "columns": {
        "id": {
          "name": "id",
          "type": "uuid",
          "primaryKey": true,
          "notNull": true,
          "default": "gen_random_uuid()"
        },
        "email": {
          "name": "email",
          "type": "text",
          "primaryKey": false,
          "notNull": true
        },
        "user": {
          "name": "user",
          "type": "text",
          "primaryKey": false,
          "notNull": true
        },
        "primary": {
          "name": "primary",
          "type": "boolean",
          "primaryKey": false,
          "notNull": true,
          "default": false
        }
      },
      "indexes": {},
      "foreignKeys": {
        "contact_user_user_username_fk": {
          "name": "contact_user_user_username_fk",
          "tableFrom": "contact",
          "columnsFrom": [
            "user"
          ],
          "tableTo": "user",
          "columnsTo": [
            "username"
          ],
          "onUpdate": "no action",
          "onDelete": "cascade"
        }
      },
      "compositePrimaryKeys": {},
      "uniqueConstraints": {},
      "policies": {},
      "checkConstraints": {},
      "isRLSEnabled": false
    },
    "public.message": {
      "name": "message",
      "schema": "",
      "columns": {
        "id": {
          "name": "id",
          "type": "uuid",
          "primaryKey": true,
          "notNull": true,
          "default": "gen_random_uuid()"
        },
        "text": {
          "name": "text",
          "type": "text",
          "primaryKey": false,
          "notNull": true
        },
        "created_at": {
          "name": "created_at",
          "type": "timestamp",
          "primaryKey": false,
          "notNull": true,
          "default": "now()"
        },
        "likes": {
          "name": "likes",
          "type": "bigint",
          "primaryKey": false,
          "notNull": true,
          "default": 0
        }
      },
      "indexes": {},
      "foreignKeys": {},
      "compositePrimaryKeys": {},
      "uniqueConstraints": {},
      "policies": {},
      "checkConstraints": {},
      "isRLSEnabled": false
    },
    "public.user": {
      "name": "user",
      "schema": "",
      "columns": {
        "username": {
          "name": "username",
          "type": "text",
          "primaryKey": false,
          "notNull": true
        },
        "password": {
          "name": "password",
          "type": "text",
          "primaryKey": false,
          "notNull": true
        },
        "firstname": {
          "name": "firstname",
          "type": "text",
          "primaryKey": false,
          "notNull": true
        },
        "lastname": {
          "name": "lastname",
          "type": "text",
          "primaryKey": false,
          "notNull": true
        }
      },
      "indexes": {},
      "foreignKeys": {},
      "compositePrimaryKeys": {},
      "uniqueConstraints": {
        "user_username_unique": {
          "name": "user_username_unique",
          "columns": [
            "username"
          ],
          "nullsNotDistinct": false
        }
      },
      "policies": {},
      "checkConstraints": {},
      "isRLSEnabled": false
    }
  },
  "enums": {},
  "schemas": {},
  "views": {},
  "sequences": {},
  "roles": {},
  "policies": {},
  "_meta": {
    "columns": {},
    "schemas": {},
    "tables": {}
  }
}